{"url":"https://api.github.com/repos/openlayers/openlayers/releases/8857940","assets_url":"https://api.github.com/repos/openlayers/openlayers/releases/8857940/assets","upload_url":"https://uploads.github.com/repos/openlayers/openlayers/releases/8857940/assets{?name,label}","html_url":"https://github.com/openlayers/openlayers/releases/tag/v4.6.4","id":8857940,"tag_name":"v4.6.4","target_commitish":"master","name":"","draft":false,"author":{"login":"ahocevar","id":211514,"avatar_url":"https://avatars1.githubusercontent.com/u/211514?v=4","gravatar_id":"","url":"https://api.github.com/users/ahocevar","html_url":"https://github.com/ahocevar","followers_url":"https://api.github.com/users/ahocevar/followers","following_url":"https://api.github.com/users/ahocevar/following{/other_user}","gists_url":"https://api.github.com/users/ahocevar/gists{/gist_id}","starred_url":"https://api.github.com/users/ahocevar/starred{/owner}{/repo}","subscriptions_url":"https://api.github.com/users/ahocevar/subscriptions","organizations_url":"https://api.github.com/users/ahocevar/orgs","repos_url":"https://api.github.com/users/ahocevar/repos","events_url":"https://api.github.com/users/ahocevar/events{/privacy}","received_events_url":"https://api.github.com/users/ahocevar/received_events","type":"User","site_admin":false},"prerelease":false,"created_at":"2017-12-11T11:11:26Z","published_at":"2018-01-02T23:39:31Z","assets":[{"url":"https://api.github.com/repos/openlayers/openlayers/releases/assets/5590536","id":5590536,"name":"v4.6.4-dist.zip","label":null,"uploader":{"login":"ahocevar","id":211514,"avatar_url":"https://avatars1.githubusercontent.com/u/211514?v=4","gravatar_id":"","url":"https://api.github.com/users/ahocevar","html_url":"https://github.com/ahocevar","followers_url":"https://api.github.com/users/ahocevar/followers","following_url":"https://api.github.com/users/ahocevar/following{/other_user}","gists_url":"https://api.github.com/users/ahocevar/gists{/gist_id}","starred_url":"https://api.github.com/users/ahocevar/starred{/owner}{/repo}","subscriptions_url":"https://api.github.com/users/ahocevar/subscriptions","organizations_url":"https://api.github.com/users/ahocevar/orgs","repos_url":"https://api.github.com/users/ahocevar/repos","events_url":"https://api.github.com/users/ahocevar/events{/privacy}","received_events_url":"https://api.github.com/users/ahocevar/received_events","type":"User","site_admin":false},"content_type":"application/zip","state":"uploaded","size":617731,"download_count":1512,"created_at":"2017-12-11T18:20:05Z","updated_at":"2017-12-11T18:20:08Z","browser_download_url":"https://github.com/openlayers/openlayers/releases/download/v4.6.4/v4.6.4-dist.zip"},{"url":"https://api.github.com/repos/openlayers/openlayers/releases/assets/5590537","id":5590537,"name":"v4.6.4.zip","label":null,"uploader":{"login":"ahocevar","id":211514,"avatar_url":"https://avatars1.githubusercontent.com/u/211514?v=4","gravatar_id":"","url":"https://api.github.com/users/ahocevar","html_url":"https://github.com/ahocevar","followers_url":"https://api.github.com/users/ahocevar/followers","following_url":"https://api.github.com/users/ahocevar/following{/other_user}","gists_url":"https://api.github.com/users/ahocevar/gists{/gist_id}","starred_url":"https://api.github.com/users/ahocevar/starred{/owner}{/repo}","subscriptions_url":"https://api.github.com/users/ahocevar/subscriptions","organizations_url":"https://api.github.com/users/ahocevar/orgs","repos_url":"https://api.github.com/users/ahocevar/repos","events_url":"https://api.github.com/users/ahocevar/events{/privacy}","received_events_url":"https://api.github.com/users/ahocevar/received_events","type":"User","site_admin":false},"content_type":"application/zip","state":"uploaded","size":20399812,"download_count":1748,"created_at":"2017-12-11T18:20:06Z","updated_at":"2017-12-11T18:20:26Z","browser_download_url":"https://github.com/openlayers/openlayers/releases/download/v4.6.4/v4.6.4.zip"}],"tarball_url":"https://api.github.com/repos/openlayers/openlayers/tarball/v4.6.4","zipball_url":"https://api.github.com/repos/openlayers/openlayers/zipball/v4.6.4","body":"# 4.6.4\r\n\r\nThe v4.6.4 release fixes a feature selection issue when `renderMode: 'image'` is set on an `ol.layer.Vector`.\r\n\r\n## Fixes\r\n\r\n * [#7559](https://github.com/openlayers/openlayers/pull/7559) - Handle skipping and unskipping features with renderMode: 'image' ([@ahocevar](https://github.com/ahocevar))\r\n"}